pycomplete/__init__.py
pycomplete/chainset.py
pycomplete/markovchain.py
pycomplete/pycomplete.py
pycomplete/trie.py
pycomplete/trienode.py
pyautocomplete-2.2.0.dist-info/METADATA
pyautocomplete-2.2.0.dist-info/WHEEL
pyautocomplete-2.2.0.dist-info/top_level.txt
pyautocomplete-2.2.0.dist-info/RECORD
