Metadata-Version: 2.4
Name: pyautocomplete
Version: 2.2.0
Summary: Autocomplete written in python
Requires-Python: >=3.12
Requires-Dist: coverage>=7.9.2
Requires-Dist: pytest>=8.4.1
Requires-Dist: pytest-timeout>=2.4.0
